siura/__init__.py
siura/auth.py
siura/base.py
siura/meli.py
siura/template.py
siura-1.1.1.dist-info/LICENSE
siura-1.1.1.dist-info/METADATA
siura-1.1.1.dist-info/WHEEL
siura-1.1.1.dist-info/top_level.txt
siura-1.1.1.dist-info/RECORD
