Metadata-Version: 2.1
Name: siura
Version: 1.1.1
Summary: SDK for SIURA
Home-page: https://github.com/siura/sdk
Author: WAMY S.A.S
Author-email: dev@siura.com
Classifier: Programming Language :: Python :: 3
Classifier: License :: OSI Approved :: MIT License
Classifier: Operating System :: OS Independent
Requires-Python: >=3.6
License-File: LICENSE
Requires-Dist: requests
Requires-Dist: python-dotenv
